[{"CapabilityId":"Oak9.CR.BR.2","CapabilityName":"","Source":"Aws","ResourceName":"es","ResourceId":"AWS::Elasticsearch-b136efe3-828a-3735-c06e-adf31fa82a6a","ResourceType":"AWS::Elasticsearch","ResourceGap":"Critical","HasResourceGap":true,"ResourceImpact":"Critical","HasResourceImpact":true,"Violations":[{"Severity":"Moderate","HasSeverity":true,"ConfigGap":"[configId] is not set to define the time in UTC when daily automatic snapshots are taken","HasConfigGap":true,"CapabilityId":"Oak9.CR.BR.2","HasCapabilityId":true,"ResourceId":"AWS::Elasticsearch-b136efe3-828a-3735-c06e-adf31fa82a6a","HasResourceId":true,"ResourceType":"AWS::Elasticsearch","HasResourceType":true,"ConfigId":"elasticsearch.domain.snapshot_options.automated_snapshot_start_hour","HasConfigId":true,"ConfigValue":"0","HasConfigValue":true,"Oak9Guidance":"https://docs.oak9.io/oak9/design-gap-documentation/aws/aws-elasticsearch#backups","HasOak9Guidance":true,"PrefferedValue":"","HasPrefferedValue":true,"CapabilityName":"","HasCapabilityName":true,"ConfigFix":"Set [configId] to the most appropriate time for taking daily snapshots depending on the use cases of the architecture","HasConfigFix":true,"ConfigImpact":"","HasConfigImpact":true}],"Oak9Guidance":"","HasOak9Guidance":false,"MappedIndustryFrameworks":[]},{"CapabilityId":"Oak9.CR.DIT.1","CapabilityName":"","Source":"Aws","ResourceName":"es","ResourceId":"AWS::Elasticsearch-b136efe3-828a-3735-c06e-adf31fa82a6a","ResourceType":"AWS::Elasticsearch","ResourceGap":"Critical","HasResourceGap":true,"ResourceImpact":"Critical","HasResourceImpact":true,"Violations":[{"Severity":"High","HasSeverity":true,"ConfigGap":"[configId] does not have value set to True to Enforce HTTPS","HasConfigGap":true,"CapabilityId":"Oak9.CR.DIT.1","HasCapabilityId":true,"ResourceId":"AWS::Elasticsearch-b136efe3-828a-3735-c06e-adf31fa82a6a","HasResourceId":true,"ResourceType":"AWS::Elasticsearch","HasResourceType":true,"ConfigId":"elasticsearch.domain.domain_endpoint_options.enforce_http_s","HasConfigId":true,"ConfigValue":"False","HasConfigValue":true,"Oak9Guidance":"https://docs.oak9.io/oak9/design-gap-documentation/aws/aws-elasticsearch#tls","HasOak9Guidance":true,"PrefferedValue":"True","HasPrefferedValue":true,"CapabilityName":"","HasCapabilityName":true,"ConfigFix":"Enable [configId] to enforce communication over a secure channel","HasConfigFix":true,"ConfigImpact":"","HasConfigImpact":true},{"Severity":"Critical","HasSeverity":true,"ConfigGap":"[configId] does not have the value set to True to enable node-to-node encryption","HasConfigGap":true,"CapabilityId":"Oak9.CR.DIT.1","HasCapabilityId":true,"ResourceId":"AWS::Elasticsearch-b136efe3-828a-3735-c06e-adf31fa82a6a","HasResourceId":true,"ResourceType":"AWS::Elasticsearch","HasResourceType":true,"ConfigId":"elasticsearch.domain.node_to_node_encryption_options.enabled","HasConfigId":true,"ConfigValue":"False","HasConfigValue":true,"Oak9Guidance":"https://docs.oak9.io/oak9/design-gap-documentation/aws/aws-elasticsearch#tls","HasOak9Guidance":true,"PrefferedValue":"True","HasPrefferedValue":true,"CapabilityName":"","HasCapabilityName":true,"ConfigFix":"Set [configId] to True to ensure node-to-node encryption is enabled ","HasConfigFix":true,"ConfigImpact":"","HasConfigImpact":true}],"Oak9Guidance":"","HasOak9Guidance":false,"MappedIndustryFrameworks":[]},{"CapabilityId":"Oak9.CR.KM.1","CapabilityName":"","Source":"Aws","ResourceName":"es","ResourceId":"AWS::Elasticsearch-b136efe3-828a-3735-c06e-adf31fa82a6a","ResourceType":"AWS::Elasticsearch","ResourceGap":"Critical","HasResourceGap":true,"ResourceImpact":"Critical","HasResourceImpact":true,"Violations":[{"Severity":"Moderate","HasSeverity":true,"ConfigGap":"[configId] does not have the value set for KMS key","HasConfigGap":true,"CapabilityId":"Oak9.CR.KM.1","HasCapabilityId":true,"ResourceId":"AWS::Elasticsearch-b136efe3-828a-3735-c06e-adf31fa82a6a","HasResourceId":true,"ResourceType":"AWS::Elasticsearch","HasResourceType":true,"ConfigId":"elasticsearch.domain.encryption_at_rest_options.kms_key_id","HasConfigId":true,"ConfigValue":"","HasConfigValue":true,"Oak9Guidance":"https://docs.oak9.io/oak9/design-gap-documentation/aws/aws-elasticsearch#protect-cryptographic-keys","HasOak9Guidance":true,"PrefferedValue":"","HasPrefferedValue":true,"CapabilityName":"","HasCapabilityName":true,"ConfigFix":"Set [configId] to use customer-managed keys for data at rest encryption in accordance with your organization's key management plan","HasConfigFix":true,"ConfigImpact":"","HasConfigImpact":true}],"Oak9Guidance":"","HasOak9Guidance":false,"MappedIndustryFrameworks":[]},{"CapabilityId":"Oak9.CR.AE.2","CapabilityName":"","Source":"Aws","ResourceName":"es","ResourceId":"AWS::Elasticsearch-b136efe3-828a-3735-c06e-adf31fa82a6a","ResourceType":"AWS::Elasticsearch","ResourceGap":"Critical","HasResourceGap":true,"ResourceImpact":"Critical","HasResourceImpact":true,"Violations":[{"Severity":"High","HasSeverity":true,"ConfigGap":"[configId] is not enabled for advanced security options","HasConfigGap":true,"CapabilityId":"Oak9.CR.AE.2","HasCapabilityId":true,"ResourceId":"AWS::Elasticsearch-b136efe3-828a-3735-c06e-adf31fa82a6a","HasResourceId":true,"ResourceType":"AWS::Elasticsearch","HasResourceType":true,"ConfigId":"elasticsearch.domain.advanced_security_options.enabled","HasConfigId":true,"ConfigValue":"False","HasConfigValue":true,"Oak9Guidance":"https://docs.oak9.io/oak9/design-gap-documentation/aws/aws-elasticsearch#access-control-policy","HasOak9Guidance":true,"PrefferedValue":"True","HasPrefferedValue":true,"CapabilityName":"","HasCapabilityName":true,"ConfigFix":"Set [configId] to True to ensure advanced security options are enabled for fine-grained access control","HasConfigFix":true,"ConfigImpact":"","HasConfigImpact":true}],"Oak9Guidance":"","HasOak9Guidance":false,"MappedIndustryFrameworks":[]},{"CapabilityId":"Oak9.CR.IA.1","CapabilityName":"","Source":"Aws","ResourceName":"es","ResourceId":"AWS::Elasticsearch-b136efe3-828a-3735-c06e-adf31fa82a6a","ResourceType":"AWS::Elasticsearch","ResourceGap":"Critical","HasResourceGap":true,"ResourceImpact":"Critical","HasResourceImpact":true,"Violations":[{"Severity":"High","HasSeverity":true,"ConfigGap":"[configId] is not set to True to enable Amazon Cognito","HasConfigGap":true,"CapabilityId":"Oak9.CR.IA.1","HasCapabilityId":true,"ResourceId":"AWS::Elasticsearch-b136efe3-828a-3735-c06e-adf31fa82a6a","HasResourceId":true,"ResourceType":"AWS::Elasticsearch","HasResourceType":true,"ConfigId":"elasticsearch.domain.cognito_options.enabled","HasConfigId":true,"ConfigValue":"False","HasConfigValue":true,"Oak9Guidance":"https://docs.oak9.io/oak9/design-gap-documentation/aws/aws-elasticsearch#identification-and-authentication","HasOak9Guidance":true,"PrefferedValue":"True","HasPrefferedValue":true,"CapabilityName":"","HasCapabilityName":true,"ConfigFix":"Set [configId] to True to enable Amazon Cognito to ensure strong authentication is in place","HasConfigFix":true,"ConfigImpact":"May result in unauthorized access","HasConfigImpact":true}],"Oak9Guidance":"","HasOak9Guidance":false,"MappedIndustryFrameworks":[]}]